complot/__init__.py
complot/version.py
complot/axes_providers/__init__.py
complot/axes_providers/asdf.py
complot/histogram/__init__.py
complot/histogram/histogram.py
complot/mpl/compostela.py
complot/others/untitled.py
complot-1.0.0.dev0.dist-info/LICENSE.txt
complot-1.0.0.dev0.dist-info/METADATA
complot-1.0.0.dev0.dist-info/WHEEL
complot-1.0.0.dev0.dist-info/top_level.txt
complot-1.0.0.dev0.dist-info/RECORD
