Metadata-Version: 2.1
Name: complot
Version: 1.0.0.dev0
Summary: Statistical and plotting tools.
Home-page: https://github.com/marromlam/complot.git
Download-URL: https://github.com/marromlam/complot.git
Author: Marcos Romero Lamas
Author-email: marromlam@gmail.com
License: MIT License Copyright (c) 2021 Marcos Romero Lamas
Keywords: statistics plotting
Platform: Linux
Platform: macOS
Platform: Windows
Requires-Python: >=3.5
License-File: LICENSE.txt
Requires-Dist: numpy
Requires-Dist: matplotlib
Requires-Dist: scipy
